woe_bin/__init__.py
woe_bin/__version__.py
woe_bin/woe_bin.py
woe_bin-1.0.2.dist-info/LICENSE
woe_bin-1.0.2.dist-info/METADATA
woe_bin-1.0.2.dist-info/WHEEL
woe_bin-1.0.2.dist-info/entry_points.txt
woe_bin-1.0.2.dist-info/top_level.txt
woe_bin-1.0.2.dist-info/RECORD
