Metadata-Version: 2.1
Name: woe-bin
Version: 1.0.2
Summary: split the continuous variable,while the ouput woe value is monotonous
Home-page: https://github.com/jinxinbo/woe_bin
Author: jinxinbo
Author-email: tmacabo@163.com
License: MIT License
Platform: UNKNOWN
Classifier: Programming Language :: Python :: 3
Classifier: License :: OSI Approved :: MIT License
Classifier: Operating System :: OS Independent
